ppp_svc_helper-0.3.13.dist-info/licenses/LICENSE.md
svc_helper/__init__.py
svc_helper/augmentation/__init__.py
svc_helper/augmentation/pedalboard.py
svc_helper/gui/__init__.py
svc_helper/gui/config.yaml
svc_helper/gui/gui.py
svc_helper/gui/utils.py
svc_helper/gui/modules/__init__.py
svc_helper/gui/modules/checkpoint.py
svc_helper/gui/modules/file_input.py
svc_helper/gui/modules/inference.py
svc_helper/gui/modules/param.py
svc_helper/gui/widgets/__init__.py
svc_helper/gui/widgets/audio_preview.py
svc_helper/gui/widgets/compact_combo_box.py
svc_helper/gui/widgets/file_button.py
svc_helper/gui/widgets/recorder.py
svc_helper/gui/widgets/stopwatch.py
svc_helper/inference/__init__.py
svc_helper/inference/silero.py
svc_helper/pitch/__init__.py
svc_helper/pitch/rmvpe.py
svc_helper/pitch/utils.py
svc_helper/sfeatures/__init__.py
svc_helper/sfeatures/models.py
svc_helper/sfeatures/svc5/__init__.py
svc_helper/sfeatures/svc5/encoder.py
svc_helper/sfeatures/svc5/hubert_model.py
svc_helper/sfeatures/svc5/vits/__init__.py
svc_helper/sfeatures/svc5/vits/attentions.py
svc_helper/sfeatures/svc5/vits/commons.py
svc_helper/sfeatures/svc5/vits/data_utils.py
svc_helper/sfeatures/svc5/vits/losses.py
svc_helper/sfeatures/svc5/vits/models.py
svc_helper/sfeatures/svc5/vits/modules.py
svc_helper/sfeatures/svc5/vits/modules_grl.py
svc_helper/sfeatures/svc5/vits/spectrogram.py
svc_helper/sfeatures/svc5/vits/utils.py
svc_helper/sfeatures/whisper/__init__.py
svc_helper/sfeatures/whisper/audio.py
svc_helper/sfeatures/whisper/decoding.py
svc_helper/sfeatures/whisper/model.py
svc_helper/sfeatures/whisper/tokenizer.py
svc_helper/sfeatures/whisper/utils.py
svc_helper/speaker/__init__.py
svc_helper/speaker/models.py
svc_helper/speaker/svc5/__init__.py
svc_helper/speaker/svc5/config.py
svc_helper/speaker/svc5/models/__init__.py
svc_helper/speaker/svc5/models/lstm.py
svc_helper/speaker/svc5/models/resnet.py
svc_helper/speaker/svc5/utils/__init__.py
svc_helper/speaker/svc5/utils/audio.py
svc_helper/speaker/svc5/utils/coqpit.py
ppp_svc_helper-0.3.13.dist-info/METADATA
ppp_svc_helper-0.3.13.dist-info/WHEEL
ppp_svc_helper-0.3.13.dist-info/top_level.txt
ppp_svc_helper-0.3.13.dist-info/RECORD
