Metadata-Version: 2.4
Name: ppp_svc_helper
Version: 0.3.13
Summary: Utility library for singing voice conversion work
Author: effusiveperiscope
Author-email: therealvul <wowitsvul@gmail.com>
License-Expression: MIT
Project-URL: Homepage, https://github.com/effusiveperiscope/svc_helper
Project-URL: Issues, https://github.com/effusiveperiscope/svc_helper/issues
Classifier: Programming Language :: Python :: 3
Classifier: Operating System :: OS Independent
Requires-Python: >=3.9
License-File: LICENSE.md
Requires-Dist: av>=10.0.0
Requires-Dist: fairseq-fixed==0.12.3.1
Requires-Dist: faiss-cpu>=1.7.4
Requires-Dist: huggingface-hub>=0.23.4
Requires-Dist: librosa>=0.10.1
Requires-Dist: numpy>=1.26.4
Requires-Dist: onnxruntime>=1.16.2
Requires-Dist: praat-parselmouth>=0.4.3
Requires-Dist: pyworld>=0.3.2
Requires-Dist: scipy>=1.14.0
Requires-Dist: setuptools>=68.2.2
Requires-Dist: soundfile>=0.12.1
Requires-Dist: torch>=2.3.1
Requires-Dist: torchcrepe>=0.0.22
Requires-Dist: PyQt5>=5.15.8
Requires-Dist: transformers>=4.52.3
Requires-Dist: silero-vad>=5.1.2
Dynamic: author
Dynamic: license-file
